freezer_dr/__init__.py
freezer_dr/main.py
freezer_dr/common/__init__.py
freezer_dr/common/config.py
freezer_dr/common/daemon.py
freezer_dr/common/osclient.py
freezer_dr/common/utils.py
freezer_dr/common/yaml_parser.py
freezer_dr/evacuators/__init__.py
freezer_dr/evacuators/common/__init__.py
freezer_dr/evacuators/common/driver.py
freezer_dr/evacuators/common/manager.py
freezer_dr/evacuators/common/utils.py
freezer_dr/evacuators/drivers/__init__.py
freezer_dr/evacuators/drivers/default/__init__.py
freezer_dr/evacuators/drivers/default/standard.py
freezer_dr/evacuators/drivers/dummy/__init__.py
freezer_dr/evacuators/drivers/dummy/dummy.py
freezer_dr/fencers/__init__.py
freezer_dr/fencers/common/__init__.py
freezer_dr/fencers/common/driver.py
freezer_dr/fencers/common/manager.py
freezer_dr/fencers/drivers/__init__.py
freezer_dr/fencers/drivers/ipmi/__init__.py
freezer_dr/fencers/drivers/ipmi/driver.py
freezer_dr/fencers/drivers/ipmi/ipmitool.py
freezer_dr/fencers/drivers/libvirt/__init__.py
freezer_dr/fencers/drivers/libvirt/driver.py
freezer_dr/monitors/__init__.py
freezer_dr/monitors/common/__init__.py
freezer_dr/monitors/common/driver.py
freezer_dr/monitors/common/manager.py
freezer_dr/monitors/drivers/__init__.py
freezer_dr/monitors/drivers/default/__init__.py
freezer_dr/monitors/drivers/default/driver.py
freezer_dr/monitors/drivers/dummy/__init__.py
freezer_dr/monitors/drivers/dummy/driver.py
freezer_dr/monitors/drivers/monasca/__init__.py
freezer_dr/monitors/drivers/monasca/driver.py
freezer_dr/notifiers/__init__.py
freezer_dr/notifiers/common/__init__.py
freezer_dr/notifiers/common/driver.py
freezer_dr/notifiers/common/manager.py
freezer_dr/notifiers/drivers/__init__.py
freezer_dr/notifiers/drivers/default/__init__.py
freezer_dr/notifiers/drivers/default/default_email.py
freezer_dr/notifiers/drivers/slack/__init__.py
freezer_dr/notifiers/drivers/slack/slack.py
freezer_dr-15.0.0.dist-info/AUTHORS
freezer_dr-15.0.0.dist-info/LICENSE
freezer_dr-15.0.0.dist-info/METADATA
freezer_dr-15.0.0.dist-info/WHEEL
freezer_dr-15.0.0.dist-info/entry_points.txt
freezer_dr-15.0.0.dist-info/pbr.json
freezer_dr-15.0.0.dist-info/top_level.txt
freezer_dr-15.0.0.dist-info/RECORD
