Metadata-Version: 2.1
Name: freezer-dr
Version: 15.0.0
Summary: OpenStack Disaster Recovery
Home-page: https://docs.openstack.org/freezer/latest/
Author: Freezer Team
Author-email: openstack-discuss@lists.openstack.org
License: UNKNOWN
Keywords: openstack,freezer,disaster,recovery,evacuation,high availability,dr
Platform: UNKNOWN
Classifier: Environment :: OpenStack
Classifier: Intended Audience :: Developers
Classifier: Intended Audience :: Information Technology
Classifier: Intended Audience :: System Administrators
Classifier: License :: OSI Approved :: Apache Software License
Classifier: Operating System :: POSIX :: Linux
Classifier: Programming Language :: Python
Classifier: Programming Language :: Python :: Implementation :: CPython
Classifier: Programming Language :: Python :: 3 :: Only
Classifier: Programming Language :: Python :: 3
Classifier: Programming Language :: Python :: 3.6
Classifier: Programming Language :: Python :: 3.7
Classifier: Programming Language :: Python :: 3.8
Classifier: Programming Language :: Python :: 3.9
Classifier: Development Status :: 5 - Production/Stable
Classifier: Natural Language :: English
Classifier: Operating System :: POSIX :: Linux
Classifier: Topic :: System :: Recovery Tools
Requires-Dist: Jinja2 (>=2.10)
Requires-Dist: PyYAML (>=3.12.0)
Requires-Dist: libvirt-python (>=1.2.5)
Requires-Dist: oslo.config (>=5.2.0)
Requires-Dist: oslo.log (>=3.36.0)
Requires-Dist: oslo.utils (>=3.33.0)
Requires-Dist: pbr (>=2.0.0)
Requires-Dist: python-keystoneclient (>=3.8.0)
Requires-Dist: python-monascaclient (>=1.1.0)
Requires-Dist: python-neutronclient (>=6.7.0)
Requires-Dist: python-novaclient (>=9.1.0)
